<HBProfile>
<Name>Mjj23's Dire Maul North Endless Farm [$Rev$]</Name>
<MinFreeBagSlots>-1</MinFreeBagSlots>
///////////////////////////////////////////////////////////////////////
// Profile Maker: Mjj23
// Farm zone: Dire Maul (North)
// Farm mobs: All
// Grind Speed: N/A
// Grind what? Saltstone Plate/Various Transmog
///////////////////////////////////////////////////////////////////////

<MinLevel>54</MinLevel>
<MaxLevel>101</MaxLevel>

<MailGrey>False</MailGrey>
<MailWhite>True</MailWhite>
<MailGreen>True</MailGreen>
<MailBlue>True</MailBlue>
<MailPurple>True</MailPurple>

<SellGrey>True</SellGrey>
<SellWhite>False</SellWhite>
<SellGreen>False</SellGreen>
<SellBlue>False</SellBlue>
<SellPurple>False</SellPurple>

	<!-- Protected Items list, can add to these as you see fit, if you are looking for specific items -->
	<ProtectedItems>
		<Item Name = "Tyrant's Chestpiece" Entry = "14835"/>
		<Item Name = "Tyrant's Breastplate" Entry = "14840"/>
		
	</ProtectedItems>
		
	<Vendors>
		<Vendor Name="Afran" Entry="40967" Type="Repair" X="-3183.528" Y="1878.203" Z="48.42564" /> <!-- Alliance -->
		<Vendor Name="Cawind Trueaim" Entry="9548" Type="Repair" X="-4484.554" Y="233.5269" Z="48.3927" /> <!-- Horde -->
	</Vendors>

	<Mailboxes>
		<Mailbox X="-3198.365" Y="1898.748" Z="49.33393" /> <!-- Alliance -->
		<Mailbox X="-4404.685" Y="238.3757" Z="26.78822" /> <!-- Horde -->
	</Mailboxes>


		<AvoidMobs>
		<Mob Name="Summon Enabler Stalker" Entry="53488" />
		<Mob Name="Gordok Spirit" Entry="11446" />
		</AvoidMobs>


<Blackspots>
	<Blackspot X="1485.6520" Y="807.7772" Z="8.8910" Radius="5" />
</Blackspots>
	

<QuestOrder>
<CustomBehavior File="UserSettings" FindVendorsAutomatically="False" LootMobs="True" PullDistance="50" KillBetweenHotspots="True" LogoutForInactivity="False" />
<If Condition="!(Me.MapId == 429)" >

		<While Condition="!(Me.MapId == 1)" >
			<If Condition="Me.IsAlliance" >
			<!-- Outland move to and use portal in shat -->
				<If Condition="Me.MapId == 530" >
				<CustomBehavior File="Message" Text="Going to Stormwind." LogColor="Lime" />
					<CustomBehavior File="FlyTo" X="-248.064" Y="930.2079" Z="84.37978" DestName="BC Portal" />
					<CustomBehavior File="MyCTM" X="-247.1655" Y="897.484" Z="84.3497" />
					<CustomBehavior File="WaitTimer" WaitTime="5000"/>
					<While Condition="Me.MapId == 530" >
						<CustomBehavior File="MyCTM" X="-245.7161" Y="896.1308" Z="84.3497" />
						<CustomBehavior File="WaitTimer" WaitTime="5000"/>
					</While>
					<CustomBehavior File="WaitTimer" WaitTime="10000"/>
				</If>
				<!-- Northrend, go home from borean -->
				<If Condition="Me.MapId == 571" >
				<CustomBehavior File="Message" Text="Going to Stormwind." LogColor="Lime" />
					<If Condition="(HasSpell(54197))">
						<CustomBehavior File="FlyTo" DestName="fly my minions fly" X="2236.118" Y="5145.615" Z="5.346904"  />
					</If>
					<CustomBehavior File="UseTransport" TransportId="190536"    
									WaitAtX="2234.375" WaitAtY="5132.568" WaitAtZ="5.343217" 
									TransportStartX="2218.391" TransportStartY="5119.589" TransportStartZ="0.04" 
									StandOnX="2223.174" StandOnY="5118.869" StandOnZ="9.43335"
									TransportEndX="-8288.816" TransportEndY="1424.703" TransportEndZ="0.04" 
									GetOffX="-8300.08" GetOffY="1405.158" GetOffZ="4.422395" />
				</If>
				<!-- Kalimdor boat from Ratchet. -->
				<If Condition="Me.MapId == 1" >
				<CustomBehavior File="Message" Text="Going to Stormwind." LogColor="Lime" />
					<If Condition="SpellManager.HasSpell(&quot;Flight Master's License&quot;)">
						<CustomBehavior File="FlyTo" X="-996.8669" Y="-3826.07" Z="5.536246" />
					</If>
					<If Condition="!SpellManager.HasSpell(&quot;Flight Master's License&quot;)">
						<RunTo X="-996.8669" Y="-3826.07" Z="5.536246" />
					</If>
					<CustomBehavior File="UseTransport" TransportId="20808"
									WaitAtX="-996.8669" WaitAtY="-3826.07" WaitAtZ="5.536246" 
									TransportStartX="-1005.613" TransportStartY="-3841.648" TransportStartZ="0.01553879"
									StandOnX="-997.3311" StandOnY="-3836.707" StandOnZ="6.030852"
									TransportEndX="-14277.75" TransportEndY="582.8661" TransportEndZ="0.03330701"
									GetOffX="-14280.88" GetOffY="566.6268" GetOffZ="6.979454" />
				</If>
				<!-- Deepholm, Taking portal. -->
				<If Condition="Me.MapId == 646" >
				<CustomBehavior File="Message" Text="Going to Stormwind." LogColor="Lime" />
					<CustomBehavior File="FlyTo" X="846.4727" Y="483.7805" Z="-19.13363" />
					<CustomBehavior File="FlyTo" X="918.0795" Y="503.5825" Z="-49.25048" />
					<RunTo X="973.6232" Y="570.9096" Z="-46.0024" />
					<CustomBehavior File="InteractWith" MobId="205272" ObjectType="Gameobject" Range="4" X="973.6232" Y="570.9096" Z="-46.0024" />
					<CustomBehavior File="WaitTimer" WaitTime="8000" GoalText="Waiting for port {TimeRemaining}" />
				</If>
				<!-- Pandaland, Taking portal. -->
				<If Condition="Me.MapId == 870" >
				<CustomBehavior File="Message" Text="Going to Stormwind." LogColor="Lime" />
					<CustomBehavior File="FlyTo" X="-311.6545" Y="-1776.63" Z="62.67051" />
					<RunTo X="-311.6545" Y="-1776.63" Z="62.67051" />
					<CustomBehavior File="InteractWith" MobId="210805" ObjectType="Gameobject" Range="4" />
					<CustomBehavior File="WaitTimer" WaitTime="5000" GoalText="Waiting for zone {TimeRemaining}" />
				</If>
				<!-- Homeland, Ally Eastern Kingdom -->
				<If Condition="Me.MapId == 0" >

					<If condition="false"><!-- If Set true will go to Northrend -->
					<CustomBehavior File="Message" Text="Going to Vikingland." LogColor="Lime" />
					
					<If Condition="SpellManager.HasSpell(&quot;Flight Master's License&quot;)">
						<CustomBehavior File="FlyTo" X="-8300.08" Y="1405.158" Z="4.422395" />
					</If>
					<CustomBehavior File="UseTransport" TransportId="190536" 
									WaitAtX="-8300.08" WaitAtY="1405.158" WaitAtZ="4.422395"
									GetOffX="2234.375" GetOffY="5132.568" GetOffZ="5.343217"
									StandOnX="-8293.091" StandOnY="1421.008" StandOnZ="9.480089"
									TransportStartX="-8288.816" TransportStartY="1424.703" TransportStartZ="0.04" 
									TransportEndX="2218.391" TransportEndY="5119.589" TransportEndZ="0.04" />	
					<CustomBehavior File="WaitTimer" WaitTime="5000" />
					</If>
					
					<If condition="false"><!-- If Set true will go to Outland -->
					<CustomBehavior File="Message" Text="Going to Outland." LogColor="Lime" />
					
					<While Condition="Me.MapId == 0" >
						<If Condition="Me.MapId == 0" >
								<If Condition="SpellManager.HasSpell(&quot;Flight Master's License&quot;)">
									<CustomBehavior File="FlyTo" X="-11895.44" Y="-3206.936" Z="-14.64132" />
								</If>
								<RunTo X="-11895.44" Y="-3206.936" Z="-14.64132" />
								<CustomBehavior File="WaitTimer" WaitTime="1000" />
							</If>
							<If Condition="Me.MapId == 0" >
								<CustomBehavior File="MyCTM" X="-11908.09" Y="-3208.854" Z="-14.83002" />
								<CustomBehavior File="WaitTimer" WaitTime="5000" />
							</If>
							<If Condition="Me.MapId == 0" >
								<CustomBehavior File="WaitTimer" WaitTime="5000" />
							</If>
					</While>
					</If>
					
					<If condition="true"> <!-- If Set true will go to Kalimdor -->
					<CustomBehavior File="Message" Text="Going to Kalimdor." LogColor="Lime" />
					
					<If Condition="SpellManager.HasSpell(&quot;Flight Master's License&quot;)">
						<CustomBehavior File="FlyTo" X="-14288.29" Y="549.3284" Z="8.689642" />
					</If>
					<If Condition="!SpellManager.HasSpell(&quot;Flight Master's License&quot;)">
						<Runto X="-14288.29" Y="549.3284" Z="8.689642" />
					</If>
					<CustomBehavior File="ForcedDismount" />
					<!-- BB dock to Ratchet -->
					<CustomBehavior File="UseTransport" TransportId="20808"
									WaitAtX="-14280.88" WaitAtY="566.6268" WaitAtZ="6.979454" 
									TransportStartX="-14277.75" TransportStartY="582.8661" TransportStartZ="0.01553879"
									StandOnX="-14270.46" StandOnY="579.9881" StandOnZ="6.088587"
									TransportEndX="-1005.613" TransportEndY="-3841.648" TransportEndZ="0.03330701"
									GetOffX="-996.8669" GetOffY="-3826.07" GetOffZ="5.536246" />
					</If>
					
					<If condition="false"><!-- If Set true will go to Pandaland -->
					<CustomBehavior File="Message" Text="Going to Pandaland." LogColor="Lime" />
					
					<CustomBehavior File="FlyTo" X="-8200.323" Y="527.858" Z="116.7516"  />
					<CustomBehavior File="InteractWith" MobId="215457" ObjectType="Gameobject" Range="4" />
					<CustomBehavior File="WaitTimer" WaitTime="5000" GoalText="Waiting for zone {TimeRemaining}" />
					<!-- Going to Pandaland Stop -->
					</If>	
					
					<!-- No profiles in deepholm-->
						
				</If>
			</If>
			<!-- Horde part -->
			<If Condition="Me.IsHorde" >
				<!-- Outland move to and use portal in shat -->
				<If Condition="Me.MapId == 530" >
				<CustomBehavior File="Message" Text="Going to Kalimdor." LogColor="Lime" />
					<While Condition="Me.MapId == 530" >
						<CustomBehavior File="FlyTo" DestName="Org portal" X="-1956.413" Y="5383.551" Z="-12.42774" />
						<CustomBehavior File="ForcedDismount" />

						<RunTo X="-1898.169" Y="5395.958" Z="-12.42774" />
						<CustomBehavior File="InteractWith" MobId="183323" ObjectType="Gameobject" Range="4" />
						<CustomBehavior File="WaitTimer" WaitTime="15000" GoalText="Waiting for zone {TimeRemaining}" />
					</While>
					<RunTo X="1896.122" Y="-4489.93" Z="23.84045" />
					<CustomBehavior File="FlyTo" X="1882.573" Y="-4548.733" Z="110.4602" />
				</If>
				<!-- Northrend, go home from borean -->
				<If Condition="Me.MapId == 571" >
				<CustomBehavior File="Message" Text="Going to Kalimdor." LogColor="Lime" />
					<If Condition="(HasSpell(54197))">
						<CustomBehavior File="FlyTo" DestName="Borean Tundra" X="2708.396" Y="6066.991" Z="109.617" />
						<CustomBehavior File="FlyTo" DestName="Warsong Hold, BT" X="2740.837" Y="6097.529" Z="76.88604" />
					</If>
					<CustomBehavior File="Message" Text="Running to Borean Zepp to Org" LogColor="Cornflowerblue" />
					<RunTo X="2829.74" Y="6179.48" Z="121.9793" />
					<CustomBehavior File="Message" Text="Waiting for Borean Zepp to Org - don't interact!" LogColor="Orange" />
					<CustomBehavior File="UseTransport" TransportId="186238"
									WaitAtX="2836.831" WaitAtY="6185.15" WaitAtZ="121.9923" 
									TransportStartX="2837.908" TransportStartY="6187.443" TransportStartZ="140.1648" 
									StandOnX="2844.171" StandOnY="6191.577" StandOnZ="122.3017" 
									TransportEndX="1775.066" TransportEndY="-4299.745" TransportEndZ="151.0326" 
									GetOffX="1763.203" GetOffY="-4284.529" GetOffZ="133.1072" />
				</If>
				<!-- From Eastern Kingdom going home -->
				<If Condition="Me.MapId == 0" >
				<CustomBehavior File="Message" Text="Going to Kalimdor." LogColor="Lime" />
					<If Condition="SpellManager.HasSpell(&quot;Flight Master's License&quot;)">
						<CustomBehavior File="FlyTo" X="2039.925" Y="273.7229" Z="142.3792" />
						<CustomBehavior File="FlyTo" X="2067.174" Y="284.9927" Z="97.03151" />
					</If>
					<RunTo X="2070.155" Y="289.2588" Z="97.0315" />
					<CustomBehavior File="UseTransport"
									TransportId="164871"
									WaitAtX="2070.155" WaitAtY="289.2588" WaitAtZ="97.0315" 
									TransportStartX="2062.376" TransportStartY="292.998" TransportStartZ="114.973"
									TransportEndX="1833.509" TransportEndY="-4391.543" TransportEndZ="152.7679"
									StandOnX="2067.979" StandOnY="295.2747" StandOnZ="97.23677" 
									GetOffX="1840.225" GetOffY="-4390.912" GetOffZ="135.2337" />
				</If>
				<!-- Deepholm, Taking portal. -->
				<If Condition="Me.MapId == 646" >
				<CustomBehavior File="Message" Text="Going to Kalimdor." LogColor="Lime" />
					<CustomBehavior File="FlyTo" X="846.4727" Y="483.7805" Z="-19.13363" />
					<CustomBehavior File="FlyTo" X="918.0795" Y="503.5825" Z="-49.25048" />
					<RunTo X="990.1199" Y="457.7099" Z="-44.2598" />
					<CustomBehavior File="InteractWith" MobId="205273" ObjectType="Gameobject" Range="4" X="990.1199" Y="457.7099" Z="-44.2598" />
					<CustomBehavior File="WaitTimer" WaitTime="8000" GoalText="Waiting for port {TimeRemaining}" />
				</If>
				<!-- Pandaland, Taking portal. -->
				<If Condition="Me.MapId == 870" >
				<CustomBehavior File="Message" Text="Going to Kalimdor." LogColor="Lime" />
				
					<CustomBehavior File="FlyTo" X="2924.921" Y="-510.5903" Z="268.8555" />
					<RunTo X="2924.921" Y="-510.5903" Z="268.8555" />
					<CustomBehavior File="InteractWith" MobId="210804" ObjectType="Gameobject" Range="4" />
					<CustomBehavior File="WaitTimer" WaitTime="5000" GoalText="Waiting for zone {TimeRemaining}" />
				</If>
				<!-- Homeland, Horde Kalimdor -->
				<If Condition="Me.MapId == 1" >

					<If condition="false"><!-- If Set true will go to Northrend -->
					<CustomBehavior File="Message" Text="Going to Northrend." LogColor="Lime" />
					
						<If Condition="SpellManager.HasSpell(&quot;Flight Master's License&quot;)">
							<CustomBehavior File="FlyTo" X="1736.402" Y="-4283.072" Z="190.7621" />
							<CustomBehavior File="FlyTo" X="1754.089" Y="-4278.742" Z="133.0416" />
							<CustomBehavior File="ForcedDismount" />
						</If>
						<RunTo X="1763.389" Y="-4283.858" Z="133.1073" />
						
						<CustomBehavior File="Message" Text="Waiting for Org Zepp to Borean - don't interact!" LogColor="Orange" />
				
						<CustomBehavior File="UseTransport" TransportId="186238"
										WaitAtX="1763.066" WaitAtY="-4284.396" WaitAtZ="133.1081" 
										TransportStartX="1775.066" TransportStartY="-4299.745" TransportStartZ="151.0326" 
										StandOnX="1770.22" StandOnY="-4292.056" StandOnZ="133.1872" 
										TransportEndX="2837.908" TransportEndY="6187.443" TransportEndZ="140.1648" 
										GetOffX="2836.831" GetOffY="6185.15" GetOffZ="121.9923" />
						<RunTo X="2740.837" Y="6097.529" Z="76.88604" />
					</If>
					
					<If condition="false"><!-- If Set true will go to Outland -->
					<CustomBehavior File="Message" Text="On out way to Outland." LogColor="Lime" />
					<CustomBehavior File="Message" Text="Going by boat in Ratchet." LogColor="Lime" />
					
					<If Condition="SpellManager.HasSpell(&quot;Flight Master's License&quot;)">
						<CustomBehavior File="FlyTo" X="-996.8669" Y="-3826.07" Z="5.536246" />
					</If>
					<If Condition="!SpellManager.HasSpell(&quot;Flight Master's License&quot;)">
						<RunTo X="-996.8669" Y="-3826.07" Z="5.536246" />
					</If>
					<CustomBehavior File="UseTransport" TransportId="20808"
									WaitAtX="-996.8669" WaitAtY="-3826.07" WaitAtZ="5.536246" 
									TransportStartX="-1005.613" TransportStartY="-3841.648" TransportStartZ="0.01553879"
									StandOnX="-997.3311" StandOnY="-3836.707" StandOnZ="6.030852"
									TransportEndX="-14277.75" TransportEndY="582.8661" TransportEndZ="0.03330701"
									GetOffX="-14280.88" GetOffY="566.6268" GetOffZ="6.979454" />
									<!-- Should now be in Eastern Kingdom -->
						<While Condition="Me.MapId == 0" >
							<If Condition="Me.MapId == 0" >
								<If Condition="SpellManager.HasSpell(&quot;Flight Master's License&quot;)">
									<CustomBehavior File="FlyTo" X="-11895.44" Y="-3206.936" Z="-14.64132" />
								</If>
								<RunTo X="-11895.44" Y="-3206.936" Z="-14.64132" />
								<CustomBehavior File="WaitTimer" WaitTime="1000" />
							</If>
							<If Condition="Me.MapId == 0" >
								<CustomBehavior File="MyCTM" X="-11908.09" Y="-3208.854" Z="-14.83002" />
								<CustomBehavior File="WaitTimer" WaitTime="5000" />
							</If>
							<If Condition="Me.MapId == 0" >
								<CustomBehavior File="WaitTimer" WaitTime="5000" />
							</If>
						</While>
					</If>
					
					<If condition="false"><!-- If Set true will go to Eastern Kingdom -->
					<CustomBehavior File="Message" Text="Going to Eastern Kingdom." LogColor="Lime" />
					
						<If Condition="SpellManager.HasSpell(&quot;Flight Master's License&quot;)">
							<CustomBehavior File="FlyTo" X="1836.794" Y="-4383.654" Z="206.7829" />
							<CustomBehavior File="FlyTo" X="1848.44" Y="-4398.829" Z="135.1602" />
							<CustomBehavior File="ForcedDismount" />
						</If>
						<RunTo X="1840.468" Y="-4392.099" Z="135.2326" />
						<CustomBehavior File="UseTransport" TransportId="164871"
										WaitAtX="1838.676" WaitAtY="-4387.965" WaitAtZ="135.2332"
										TransportStartX="1833.509" TransportStartY="-4391.543" TransportStartZ="152.7679"
										TransportEndX="2062.376" TransportEndY="292.998" TransportEndZ="114.973"
										StandOnX="1834.961" StandOnY="-4385.694" StandOnZ="135.0334" 
										GetOffX="2066.773" GetOffY="288.873" GetOffZ="97.03159" />
					</If>
					
					<If condition="false"><!-- If Set true will go to Pandaland -->
					<CustomBehavior File="Message" Text="Going to Pandaland." LogColor="Lime" />
					
						<CustomBehavior File="FlyTo" X="2012.948" Y="-4698.641" Z="28.60529" />
						<CustomBehavior File="InteractWith" MobId="215424" ObjectType="Gameobject" Range="4" />
						<CustomBehavior File="WaitTimer" WaitTime="5000" GoalText="Waiting for zone {TimeRemaining}" />
						
					</If>	
					
					<!-- No profiles in deepholm-->
						
				</If>
			</If>
		</While>
		<!-- 
		End transport script credit to Bengan. 
		With use of Kicks go to profiles.
		Big thanks to Kick for this.
		--> 
		
		<!-- Travel to Dire Maul (North) --> 
</If>
<While Condition="true" >
	<If Condition="!(Me.MapId == 429)" >
 		<While Condition="(Me.MapId == 1)" >
		
						<CustomBehavior File="Message" Text="Moving to Dire Maul (North) Location." LogColor="Lime" />
						<CustomBehavior File="FlyTo" DestName="Dire Maul (North)" X="-3519.844" Y="1098.864" Z="161.026" />
						<CustomBehavior File="MyCTM" X="-3519.844" Y="1094.864" Z="161.026" />
						<CustomBehavior File="WaitTimer" WaitTime="15000" />
						<CustomBehavior File="ForcedDismount" />
		</While>
	</If>
		<!-- Begin Instance Grind -->	
		<While Condition="(Me.MapId == 429)" >
						<CustomBehavior File="Misc\InstanceTimer" Timer="Start" />
						<RunTo X="259.7697" Y="-31.65197" Z="-2.5596" />
						<RunTo X="295.1591" Y="-68.91334" Z="-3.886934" />
						<RunTo X="352.2098" Y="-107.4893" Z="-3.886914" />
						<RunTo X="467.0609" Y="-64.8165" Z="-3.886914" />
						<RunTo X="464.4155" Y="0.5903826" Z="-3.907092" />
						<RunTo X="407.5555" Y="25.23149" Z="-25.43948" />
						<RunTo X="358.5423" Y="30.26973" Z="-24.93585" />
						<RunTo X="357.6159" Y="-57.33456" Z="-25.96548" />
						<RunTo X="411.8119" Y="-48.66768" Z="-23.15144" />
						<RunTo X="377.4171" Y="-12.89994" Z="-25.18369" /> <!-- Kill 1st Boss -->
						<RunTo X="412.14" Y="-1.868421" Z="-24.62733" />
						<RunTo X="468.8189" Y="10.48983" Z="-3.915042" />
						<RunTo X="470.7666" Y="63.42831" Z="-3.886911" />
						<RunTo X="489.7404" Y="96.21218" Z="-2.581882" /> <!-- Kill 2nd Boss -->
						<RunTo X="396.7097" Y="106.1529" Z="-3.886382" />
						<RunTo X="383.5477" Y="137.7518" Z="-2.403335" />
						<RunTo X="407.9969" Y="176.8091" Z="2.852952" />
						<RunTo X="443.7772" Y="135.6291" Z="-2.584653" />
						<RunTo X="482.5298" Y="174.8879" Z="2.852973" />
						<RunTo X="474.7742" Y="252.6805" Z="3.659423" />
						<RunTo X="481.986" Y="317.993" Z="2.852417" />
						<RunTo X="445.9945" Y="349.4344" Z="2.852417" />
						<RunTo X="406.618" Y="334.8925" Z="2.850941" />
						<RunTo X="387.0246" Y="314.8111" Z="11.22241" />
						<RunTo X="383.0612" Y="259.9407" Z="11.43955" /> <!-- Begin Kill 3rd Boss -->
						<RunTo X="339.3554" Y="210.1805" Z="11.20366" />
						<RunTo X="382.3431" Y="200.9193" Z="11.21689" />
						<RunTo X="385.8849" Y="253.5398" Z="11.43954" />
						<RunTo X="325.7581" Y="299.0823" Z="11.20399" />
						<RunTo X="441.4382" Y="300.9695" Z="11.20338" />
						<RunTo X="388.1885" Y="257.6944" Z="11.43957" />
						<RunTo X="420.9334" Y="202.4041" Z="11.21093" />
						<RunTo X="384.8456" Y="313.1972" Z="11.22001" /> <!-- End Kill 3rd Boss -->
						<RunTo X="383.5557" Y="369.3245" Z="-0.1871943" />
						<CustomBehavior File="InteractWith" MobId="177219" ObjectType="GameObject" X="385.3268" Y="374.2315" Z="-0.1840135" /> <!-- Open Door -->
						<RunTo X="385.4897" Y="394.073" Z="-1.67664" />
						<RunTo X="383.9091" Y="462.8903" Z="-7.232197" />
						<RunTo X="420.3491" Y="540.4078" Z="-18.34318" />
						<RunTo X="478.0688" Y="542.9188" Z="-25.36841" />
						<RunTo X="580.9041" Y="545.3105" Z="-25.39972" /> <!-- Kill 4th Boss -->
						<RunTo X="530.5211" Y="584.3451" Z="-25.40266" />
						<RunTo X="569.2982" Y="601.7975" Z="-4.754638" />
						<RunTo X="581.075" Y="569.9071" Z="-4.754638" />
						<RunTo X="484.3763" Y="562.8719" Z="27.91177" />
						<RunTo X="486.0189" Y="528.3035" Z="27.91302" />
						<RunTo X="490.7765" Y="518.1264" Z="29.46263" />
						<CustomBehavior File="InteractWith" MobId="177217" ObjectType="GameObject" X="491.2043" Y="515.1331" Z="29.46753" /> <!-- Open Inner Door -->
						<RunTo X="491.522" Y="497.2397" Z="29.46263" />
						<RunTo X="563.5868" Y="480.7864" Z="29.46277" />
						<RunTo X="621.4722" Y="481.5169" Z="29.46277" /> <!-- Kill 5th Boss -->
						<RunTo X="666.9857" Y="466.5146" Z="29.45624" />
						<RunTo X="683.8406" Y="503.2158" Z="29.46092" />
						<RunTo X="720.4388" Y="488.9828" Z="28.17859" />
						<RunTo X="740.0137" Y="434.5104" Z="28.18003" />
						<RunTo X="827.6661" Y="484.6625" Z="37.31861" /> <!-- Kill Last Boss -->
						<RunTo X="284.575" Y="36.7755" Z="-2.763682" />
						<CustomBehavior File="Message" Text="Moving to Reset Instance" LogColor="Lime" />
						<RunTo X="255.522" Y="-15.48237" Z="-2.560003"  />
						<CustomBehavior File="Misc\InstanceTimer" Timer="Check" WaitTime="369000" />
						<CustomBehavior File="MyCTM" X="255.5269" Y="-11.92353" Z="-2.560003" />
						<CustomBehavior File="WaitTimer" WaitTime="15000" />
						<CustomBehavior File="RunMacro" Macro="/script ResetInstances()" />
		</While>	
		<!-- Check bags to see if full.  Vendor using Mammoth if available before flying to mailbox -->	
			<If Condition="(HasSpell(61447) || (HasSpell(61425))" >
					<CustomBehavior File="ForceSetVendor" DoMail="False" DoRepair="True" DoSell="True" DoTrain="False" />
			</If>
			
			<If Condition="(Me.FreeBagSlots &lt;= 15) || (Me.LowestDurabilityPercent &gt; 20.0 &amp;&amp; Me.IsAlliance)" >
					<CustomBehavior File="Message" Text="Moving to Feralas Alliance Mailbox" LogColor="Lime" />
					<CustomBehavior File="FlyTo" DestName="Feralas" X="-3198.365" Y="1898.748" Z="49.33393" />
					<CustomBehavior File="ForceSetVendor" DoMail="True" DoRepair="True" DoSell="True" DoTrain="False" />
			</If>
			
			<If Condition="(Me.FreeBagSlots &lt;= 15) || (Me.LowestDurabilityPercent &gt; 20.0 &amp;&amp; Me.IsHorde)" >
					<CustomBehavior File="Message" Text="Moving to Feralas Horde Mailbox" LogColor="Lime" />
					<CustomBehavior File="FlyTo" DestName="Feralas" X="-4404.685" Y="238.3757" Z="26.78822" />
					<CustomBehavior File="ForceSetVendor" DoMail="True" DoRepair="True" DoSell="True" DoTrain="False" />
			</If>
		<!-- End bag check -->
			
			
			
</While>
				
</QuestOrder>

</HBProfile>